README.txt
setup.py
boois_conf_parser/__init__.py
boois_conf_parser/conf_parser.py
boois_conf_parser.egg-info/PKG-INFO
boois_conf_parser.egg-info/SOURCES.txt
boois_conf_parser.egg-info/dependency_links.txt
boois_conf_parser.egg-info/top_level.txt
boois_conf_parser.egg-info/zip-safe