Metadata-Version: 1.1
Name: boois-conf-parser
Version: 1.1.2
Summary: boois_conf_parser
Home-page: http://www.boois.cn/
Author: boois
Author-email: admin@boois.cn
License: MIT
Keywords: boois_conf_parser
Platform: UNKNOWN
Classifier: License :: OSI Approved :: MIT License
Classifier: Programming Language :: Python
Classifier: Intended Audience :: Developers
Classifier: Operating System :: OS Independent
